elasticsearch_django/__init__.py
elasticsearch_django/admin.py
elasticsearch_django/apps.py
elasticsearch_django/context_managers.py
elasticsearch_django/decorators.py
elasticsearch_django/index.py
elasticsearch_django/management/__init__.py
elasticsearch_django/management/commands/__init__.py
elasticsearch_django/management/commands/create_search_index.py
elasticsearch_django/management/commands/delete_search_index.py
elasticsearch_django/management/commands/prune_search_index.py
elasticsearch_django/management/commands/rebuild_search_index.py
elasticsearch_django/management/commands/update_search_index.py
elasticsearch_django/mappings/README.md
elasticsearch_django/migrations/0001_initial.py
elasticsearch_django/migrations/0002_searchquery_duration.py
elasticsearch_django/migrations/0003_auto_20160926_2021.py
elasticsearch_django/migrations/0004_auto_20161129_1135.py
elasticsearch_django/migrations/0005_convert_JSONFields.py
elasticsearch_django/migrations/0006_add_encoder_JSONField_kwarg.py
elasticsearch_django/migrations/0007_update_json_field_encoders.py
elasticsearch_django/migrations/0008_searchquery_search_terms.py
elasticsearch_django/migrations/0009_searchquery_query_type.py
elasticsearch_django/migrations/0010_searchquery_total_hits_relation.py
elasticsearch_django/migrations/0011_searchquery_aggregations.py
elasticsearch_django/migrations/0012_alter_searchquery_aggregations_and_more.py
elasticsearch_django/migrations/__init__.py
elasticsearch_django/models.py
elasticsearch_django/py.typed
elasticsearch_django/settings.py
elasticsearch_django/signals.py
elasticsearch_django-8.7.0.dist-info/METADATA
elasticsearch_django-8.7.0.dist-info/WHEEL
elasticsearch_django-8.7.0.dist-info/licenses/LICENSE
elasticsearch_django-8.7.0.dist-info/RECORD
